opsci_toolbox/__init__.py
opsci_toolbox/apis/__init__.py
opsci_toolbox/apis/rapidapi_helpers.py
opsci_toolbox/apis/reddit.py
opsci_toolbox/apis/telegram.py
opsci_toolbox/apis/webscraping.py
opsci_toolbox/apis/youtube_helpers.py
opsci_toolbox/helpers/__init__.py
opsci_toolbox/helpers/common.py
opsci_toolbox/helpers/cv.py
opsci_toolbox/helpers/dataviz.py
opsci_toolbox/helpers/dates.py
opsci_toolbox/helpers/gliner.py
opsci_toolbox/helpers/nlp.py
opsci_toolbox/helpers/nlp_cuml.py
opsci_toolbox/helpers/sna.py
opsci_toolbox/helpers/sql.py
opsci_toolbox/helpers/surreaction.py
opsci_toolbox/lexicons/__init__.py
opsci_toolbox/lexicons/stop_words_en.csv
opsci_toolbox/lexicons/stop_words_fr.csv
opsci_toolbox-0.0.19.dist-info/METADATA
opsci_toolbox-0.0.19.dist-info/WHEEL
opsci_toolbox-0.0.19.dist-info/dependency_links.txt
opsci_toolbox-0.0.19.dist-info/top_level.txt
opsci_toolbox-0.0.19.dist-info/RECORD
