Metadata-Version: 2.1
Name: opsci-toolbox
Version: 0.0.19
Summary: a complete toolbox
Home-page: UNKNOWN
Author: Erwan Le Nagard
Author-email: erwan@opsci.ai
License: MIT
Platform: UNKNOWN
Requires-Dist: requests <3,>=2.31.0
Requires-Dist: beautifulsoup4 ==4.9.3
Requires-Dist: chardet >=4.0.0
Requires-Dist: chart-studio ==1.1.0
Requires-Dist: eldar ==0.0.8
Requires-Dist: emoji ==2.10.1
Requires-Dist: fa2-modified ==0.3.10
Requires-Dist: google-api-python-client ==2.122.0
Requires-Dist: gspread ==6.1.2
Requires-Dist: hdbscan ==0.8.33
Requires-Dist: jusText ==3.0.0
Requires-Dist: langchain ==0.1.20
Requires-Dist: matplotlib >=3.9.0
Requires-Dist: mysql-connector-python >=9.0.0
Requires-Dist: networkx ==3.2.1
Requires-Dist: nltk ==3.8.1
Requires-Dist: numpy <1.25.0,>=1.21.5
Requires-Dist: opencv-python-headless ==4.9.0.80
Requires-Dist: openpyxl ==3.1.3
Requires-Dist: pandas >=1.5.3
Requires-Dist: Pillow >=9.0.1
Requires-Dist: plotly ==5.19.0
Requires-Dist: protobuf ==4.23.4
Requires-Dist: pyarrow >=14.0.2
Requires-Dist: python-louvain ==0.16
Requires-Dist: scikit-learn ==1.4.1.post1
Requires-Dist: scipy <2.0.0,>=1.8.0
Requires-Dist: sentence-transformers ==2.5.1
Requires-Dist: setuptools ==59.6.0
Requires-Dist: spacy ==3.7.4
Requires-Dist: spacy-language-detection ==0.2.1
Requires-Dist: spacymoji ==3.1.0
Requires-Dist: supervision ==0.21.0
Requires-Dist: textacy ==0.13.0
Requires-Dist: torch >=2.4.0
Requires-Dist: tqdm >=4.66.2
Requires-Dist: trafilatura ==1.7.0
Requires-Dist: transformers ==4.38.2
Requires-Dist: umap-learn ==0.5.5
Requires-Dist: urlextract ==1.9.0
Requires-Dist: wordcloud ==1.9.3
Requires-Dist: Unidecode ==1.3.8
Requires-Dist: kaleido ==0.2.1
Requires-Dist: gliner ==0.2.8
